README.md
setup.py
libpytools/__init__.py
libpytools/github_api.py
pkg_libpytools.egg-info/PKG-INFO
pkg_libpytools.egg-info/SOURCES.txt
pkg_libpytools.egg-info/dependency_links.txt
pkg_libpytools.egg-info/not-zip-safe
pkg_libpytools.egg-info/requires.txt
pkg_libpytools.egg-info/top_level.txt